{
  "project_info": {
    "project_number": "263062311326",
    "project_id": "mindmend-2",
    "storage_bucket": "mindmend-2.firebasestorage.app"
  },
  "client": [
    {
      "client_info": {
        "mobilesdk_app_id": "1:263062311326:android:e85ce78018a05e6406068f",
        "android_client_info": {
          "package_name": "com.example.myapp"
        }
      },
      "oauth_client": [
        {
          "client_id": "263062311326-2clc27h6ap1vnaatu2n6r58op8lom1cd.apps.googleusercontent.com",
          "client_type": 3
        }
      ],
      "api_key": [
        {
          "current_key": "AIzaSyDgn2mxCTNTOalqsRtuwx5KWu0T6wV8sKM"
        }
      ],
      "services": {
        "appinvite_service": {
          "other_platform_oauth_client": [
            {
              "client_id": "263062311326-2clc27h6ap1vnaatu2n6r58op8lom1cd.apps.googleusercontent.com",
              "client_type": 3
            }
          ]
        }
      }
    }
  ],
  "configuration_version": "1"
}